{"traits":["decimalLatitude","decimalLongitude","name"],"values":[{"decimalLatitude":59.8257,"decimalLongitude":17.6663,"name":"Capreolus"},{"decimalLatitude":57.1161,"decimalLongitude":15.3749,"name":"Mustela"},{"decimalLatitude":57.7868,"decimalLongitude":14.2729,"name":"Lepus"},{"decimalLatitude":67.8502,"decimalLongitude":20.3288,"name":"Sciurus"},{"decimalLatitude":59.8222,"decimalLongitude":17.7072,"name":"Lepus"},{"decimalLatitude":59.6633,"decimalLongitude":6.3757,"name":"Apodemus"},{"decimalLatitude":58.8377,"decimalLongitude":8.7322,"name":"Lepus"},{"decimalLatitude":60.81,"decimalLongitude":11.7014,"name":"Capreolus"},{"decimalLatitude":68.7622,"decimalLongitude":14.7042,"name":"Lutra"},{"decimalLatitude":60.0859,"decimalLongitude":10.0789,"name":"Sciurus"},{"decimalLatitude":59.9839,"decimalLongitude":5.9334,"name":"Phocoena"},{"decimalLatitude":63.2497,"decimalLongitude":10.4425,"name":"Lepus"},{"decimalLatitude":68.1037,"decimalLongitude":15.5195,"name":"Alces"},{"decimalLatitude":59.1688,"decimalLongitude":10.2658,"name":"Sorex"},{"decimalLatitude":62.8245,"decimalLongitude":10.1118,"name":"Lepus"},{"decimalLatitude":57.6876,"decimalLongitude":11.9477,"name":"Rattus"},{"decimalLatitude":59.607,"decimalLongitude":16.4414,"name":"Sciurus"},{"decimalLatitude":59.233,"decimalLongitude":18.3013,"name":"Dama"},{"decimalLatitude":59.3973,"decimalLongitude":17.9633,"name":"Sciurus"},{"decimalLatitude":63.8212,"decimalLongitude":20.3345,"name":"Sciurus"},{"decimalLatitude":63.8096,"decimalLongitude":20.339,"name":"Alces"},{"decimalLatitude":62.4164,"decimalLongitude":17.7332,"name":"Lutra"},{"decimalLatitude":56.1951,"decimalLongitude":16.4009,"name":"Phoca"},{"decimalLatitude":59.8007,"decimalLongitude":17.5902,"name":"Capreolus"},{"decimalLatitude":59.8536,"decimalLongitude":17.6306,"name":"Sciurus"},{"decimalLatitude":59.836,"decimalLongitude":17.7039,"name":"Capreolus"},{"decimalLatitude":57.6777,"decimalLongitude":11.931,"name":"Sciurus"},{"decimalLatitude":59.3462,"decimalLongitude":18.1055,"name":"Oryctolagus"},{"decimalLatitude":56.6042,"decimalLongitude":14.1722,"name":"Vulpes"},{"decimalLatitude":59.7539,"decimalLongitude":16.9668,"name":"Capreolus"},{"decimalLatitude":58.8002,"decimalLongitude":17.7907,"name":"Halichoerus"},{"decimalLatitude":59.8302,"decimalLongitude":17.6649,"name":"Vulpes"},{"decimalLatitude":56.9157,"decimalLongitude":14.8543,"name":"Sciurus"},{"decimalLatitude":59.8435,"decimalLongitude":16.8149,"name":"Capreolus"},{"decimalLatitude":47.3952,"decimalLongitude":-122.4662,"name":"Procyon"},{"decimalLatitude":-30.3407,"decimalLongitude":30.7331,"name":"Procavia"},{"decimalLatitude":32.3376,"decimalLongitude":-85.2088,"name":"Geomys"},{"decimalLatitude":41.4053,"decimalLongitude":-82.3364,"name":"Sciurus"},{"decimalLatitude":38.8071,"decimalLongitude":-77.2727,"name":"Vulpes"},{"decimalLatitude":28.4753,"decimalLongitude":-81.4648,"name":"Didelphis"},{"decimalLatitude":45.3739,"decimalLongitude":-75.7956,"name":"Sciurus"},{"decimalLatitude":51.1983,"decimalLongitude":6.233,"name":"Ondatra"},{"decimalLatitude":-27.5255,"decimalLongitude":152.8791,"name":"Trichosurus"},{"decimalLatitude":35.1987,"decimalLongitude":-89.7604,"name":"Sciurus"},{"decimalLatitude":25.9097,"decimalLongitude":-81.2151,"name":"Trichechus"},{"decimalLatitude":37.0475,"decimalLongitude":-121.4256,"name":"Puma"},{"decimalLatitude":38.8727,"decimalLongitude":-121.3128,"name":"Canis"},{"decimalLatitude":32.8445,"decimalLongitude":-97.4715,"name":"Odocoileus"},{"decimalLatitude":-35.2,"decimalLongitude":149.3,"name":"Macropus"},{"decimalLatitude":52.5027,"decimalLongitude":10.5606,"name":"Castor"},{"decimalLatitude":52.3206,"decimalLongitude":10.4322,"name":"Sus"},{"decimalLatitude":31.3068,"decimalLongitude":-97.3619,"name":"Sciurus"},{"decimalLatitude":39.9687,"decimalLongitude":-105.1469,"name":"Cynomys"},{"decimalLatitude":11.5309,"decimalLongitude":1.4259,"name":"Panthera"},{"decimalLatitude":37.4682,"decimalLongitude":-122.2855,"name":"Odocoileus"},{"decimalLatitude":47.723,"decimalLongitude":13.0087,"name":"Rupicapra"},{"decimalLatitude":45.1771,"decimalLongitude":7.3038,"name":"Vulpes"},{"decimalLatitude":34.2781,"decimalLongitude":-118.8032,"name":"Otospermophilus"},{"decimalLatitude":32.771,"decimalLongitude":-117.114,"name":"Canis"},{"decimalLatitude":37.0847,"decimalLongitude":-122.0627,"name":"Sylvilagus"},{"decimalLatitude":27.8066,"decimalLongitude":-81.5555,"name":"Dasypus"},{"decimalLatitude":30.3679,"decimalLongitude":-88.8235,"name":"Procyon"},{"decimalLatitude":37.2029,"decimalLongitude":-76.7364,"name":"Procyon"},{"decimalLatitude":38.9086,"decimalLongitude":-90.135,"name":"Sciurus"},{"decimalLatitude":34.0296,"decimalLongitude":-118.6832,"name":"Phoca"},{"decimalLatitude":32.2545,"decimalLongitude":-110.9995,"name":"Canis"},{"decimalLatitude":42.3654,"decimalLongitude":-71.2588,"name":"Sciurus"},{"decimalLatitude":45.4455,"decimalLongitude":-75.652,"name":"Procyon"},{"decimalLatitude":35.6326,"decimalLongitude":-82.5555,"name":"Sciurus"},{"decimalLatitude":32.8418,"decimalLongitude":-116.2257,"name":"Dipodomys"},{"decimalLatitude":35.0113,"decimalLongitude":135.6767,"name":"Macaca"},{"decimalLatitude":-33.8,"decimalLongitude":151.1,"name":"Diprotodontia"},{"decimalLatitude":-28.6,"decimalLongitude":153.5,"name":"Diprotodontia"},{"decimalLatitude":-28.5,"decimalLongitude":153.5,"name":"Diprotodontia"},{"decimalLatitude":-33.8,"decimalLongitude":151.2,"name":"Pseudocheirus"},{"decimalLatitude":-37.642,"decimalLongitude":145.5765,"name":"Wallabia"},{"decimalLatitude":-38.4823,"decimalLongitude":145.2817,"name":"Trichosurus"},{"decimalLatitude":-28.937,"decimalLongitude":152.6098,"name":"Notamacropus"},{"decimalLatitude":48.427,"decimalLongitude":-123.3013,"name":"Phoca"},{"decimalLatitude":30.2842,"decimalLongitude":-95.6551,"name":"Dasypus"},{"decimalLatitude":-32.704,"decimalLongitude":116.6898,"name":"Macropus"},{"decimalLatitude":32.8291,"decimalLongitude":-96.7147,"name":"Myocastor"},{"decimalLatitude":45.5128,"decimalLongitude":-75.3468,"name":"Procyon"},{"decimalLatitude":34.1619,"decimalLongitude":-80.8963,"name":"Sciurus"},{"decimalLatitude":69.989,"decimalLongitude":23.2831,"name":"Lutra"},{"decimalLatitude":12.4861,"decimalLongitude":2.4614,"name":"Panthera"},{"decimalLatitude":0.222,"decimalLongitude":36.8894,"name":"Equus"},{"decimalLatitude":45.4879,"decimalLongitude":8.6506,"name":"Myocastor"},{"decimalLatitude":-19.0049,"decimalLongitude":16.3727,"name":"Oryx"},{"decimalLatitude":33.0806,"decimalLongitude":-116.3593,"name":"Chaetodipus"},{"decimalLatitude":39.7634,"decimalLongitude":-74.1011,"name":"Phoca"},{"decimalLatitude":29.1606,"decimalLongitude":-98.1299,"name":"Procyon"},{"decimalLatitude":42.328,"decimalLongitude":-72.543,"name":"Sciurus"},{"decimalLatitude":42.328,"decimalLongitude":-72.543,"name":"Sciurus"},{"decimalLatitude":-18.9977,"decimalLongitude":48.5606,"name":"Indri"},{"decimalLatitude":9.1221,"decimalLongitude":-79.7756,"name":"Cebus"},{"decimalLatitude":33.3841,"decimalLongitude":-86.8713,"name":"Sciurus"},{"decimalLatitude":29.31,"decimalLongitude":-82.43,"name":"Lontra"},{"decimalLatitude":37.4084,"decimalLongitude":-122.1655,"name":"Otospermophilus"},{"decimalLatitude":42.4061,"decimalLongitude":-85.381,"name":"Odocoileus"},{"decimalLatitude":33.1868,"decimalLongitude":-116.3188,"name":"Lepus"},{"decimalLatitude":44.4392,"decimalLongitude":-77.303,"name":"Erethizon"},{"decimalLatitude":30.0841,"decimalLongitude":-95.6949,"name":"Odocoileus"},{"decimalLatitude":30.6355,"decimalLongitude":-95.5142,"name":"Sus"},{"decimalLatitude":-24.1423,"decimalLongitude":31.6846,"name":"Crocuta"},{"decimalLatitude":42.4575,"decimalLongitude":-83.9957,"name":"Sciurus"},{"decimalLatitude":34.5247,"decimalLongitude":-114.3909,"name":"Canis"},{"decimalLatitude":6.8058,"decimalLongitude":-74.2134,"name":"Metachirus"},{"decimalLatitude":6.8039,"decimalLongitude":-74.2129,"name":"Dasyprocta"},{"decimalLatitude":35.6089,"decimalLongitude":-82.4907,"name":"Procyon"},{"decimalLatitude":-45.7692,"decimalLongitude":170.6998,"name":"Arctocephalus"},{"decimalLatitude":7.5622,"decimalLongitude":-10.8367,"name":"Piliocolobus"},{"decimalLatitude":6.8058,"decimalLongitude":-74.2134,"name":"Pecari"},{"decimalLatitude":-36.6233,"decimalLongitude":149.3826,"name":"Trichosurus"},{"decimalLatitude":-30.5542,"decimalLongitude":152.1953,"name":"Antechinus"},{"decimalLatitude":-37.3566,"decimalLongitude":149.7152,"name":"Petaurus"},{"decimalLatitude":-28.6273,"decimalLongitude":153.3914,"name":"Nyctimene"},{"decimalLatitude":-28.3893,"decimalLongitude":153.3233,"name":"Trichosurus"},{"decimalLatitude":-32.7369,"decimalLongitude":151.5743,"name":"Austronomus"},{"decimalLatitude":-32.4249,"decimalLongitude":150.8766,"name":"Trichosurus"},{"decimalLatitude":-31.3948,"decimalLongitude":151.878,"name":"Chalinolobus"},{"decimalLatitude":-35.6028,"decimalLongitude":149.5221,"name":"Petauroides"},{"decimalLatitude":-35.2977,"decimalLongitude":150.3923,"name":"Petaurus"},{"decimalLatitude":-36.0007,"decimalLongitude":148.4366,"name":"Wallabia"},{"decimalLatitude":-32.422,"decimalLongitude":150.879,"name":"Canis"},{"decimalLatitude":-31.3448,"decimalLongitude":152.8077,"name":"Trichosurus"},{"decimalLatitude":-35.9918,"decimalLongitude":148.4594,"name":"Oryctolagus"},{"decimalLatitude":-30.2073,"decimalLongitude":152.7414,"name":"Phascolarctos"},{"decimalLatitude":-30.7041,"decimalLongitude":152.7185,"name":"Pteropus"},{"decimalLatitude":-28.9931,"decimalLongitude":153.4368,"name":"Phascolarctos"},{"decimalLatitude":-32.3876,"decimalLongitude":150.889,"name":"Macropus"},{"decimalLatitude":-37.3216,"decimalLongitude":149.7255,"name":"Petaurus"},{"decimalLatitude":-33.8823,"decimalLongitude":150.9525,"name":"Rattus"},{"decimalLatitude":-35.6023,"decimalLongitude":149.5201,"name":"Petauroides"},{"decimalLatitude":-34.3043,"decimalLongitude":150.9264,"name":"Wallabia"},{"decimalLatitude":-29.0723,"decimalLongitude":153.033,"name":"Notamacropus"},{"decimalLatitude":-32.7015,"decimalLongitude":152.0644,"name":"Phascolarctos"},{"decimalLatitude":-33.6931,"decimalLongitude":150.8752,"name":"Rhinolophus"},{"decimalLatitude":-29.0748,"decimalLongitude":153.0339,"name":"Antechinus"},{"decimalLatitude":-36.5815,"decimalLongitude":149.3853,"name":"Vombatus"},{"decimalLatitude":-36.5994,"decimalLongitude":149.362,"name":"Macropus"},{"decimalLatitude":-36.6015,"decimalLongitude":149.3637,"name":"Macropus"},{"decimalLatitude":-33.4162,"decimalLongitude":150.2604,"name":"Vombatus"},{"decimalLatitude":-36.5827,"decimalLongitude":149.3855,"name":"Vombatus"},{"decimalLatitude":29.8237,"decimalLongitude":-95.6235,"name":"Sciurus"},{"decimalLatitude":51.7273,"decimalLongitude":5.5834,"name":"Pipistrellus"},{"decimalLatitude":51.7271,"decimalLongitude":5.585,"name":"Pipistrellus"},{"decimalLatitude":56.492,"decimalLongitude":38.4131,"name":"Castor"},{"decimalLatitude":57.0709,"decimalLongitude":-4.1698,"name":"Cervus"},{"decimalLatitude":52.1523,"decimalLongitude":1.4045,"name":"Eptesicus"},{"decimalLatitude":47.2516,"decimalLongitude":4.7851,"name":"Sus"},{"decimalLatitude":44.6551,"decimalLongitude":-63.7646,"name":"Tamiasciurus"},{"decimalLatitude":44.6553,"decimalLongitude":-63.7318,"name":"Tamiasciurus"},{"decimalLatitude":35.7677,"decimalLongitude":-78.6962,"name":"Sciurus"},{"decimalLatitude":53.2616,"decimalLongitude":-3.5756,"name":"Erinaceus"},{"decimalLatitude":54.3813,"decimalLongitude":-1.9303,"name":"Plecotus"},{"decimalLatitude":51.5575,"decimalLongitude":-3.2275,"name":"Vulpes"},{"decimalLatitude":55.9619,"decimalLongitude":-4.6529,"name":"Sciurus"},{"decimalLatitude":57.139,"decimalLongitude":-2.1594,"name":"Sciurus"},{"decimalLatitude":53.765,"decimalLongitude":-1.4631,"name":"Talpa"},{"decimalLatitude":53.7841,"decimalLongitude":-0.6642,"name":"Mustela"},{"decimalLatitude":56.4272,"decimalLongitude":-2.8747,"name":"Sciurus"},{"decimalLatitude":54.3694,"decimalLongitude":-3.3284,"name":"Talpa"},{"decimalLatitude":52.9778,"decimalLongitude":-2.3998,"name":"Apodemus"},{"decimalLatitude":51.3434,"decimalLongitude":0.4764,"name":"Sciurus"},{"decimalLatitude":52.68,"decimalLongitude":-3.1,"name":"Meles"},{"decimalLatitude":52.0175,"decimalLongitude":0.4715,"name":"Dama"},{"decimalLatitude":53.3726,"decimalLongitude":-0.8456,"name":"Vulpes"},{"decimalLatitude":28.8271,"decimalLongitude":-103.63,"name":"Procyon"},{"decimalLatitude":49.68,"decimalLongitude":6.19,"name":"Meles"},{"decimalLatitude":53.3,"decimalLongitude":6.15,"name":"Capreolus"},{"decimalLatitude":53.1,"decimalLongitude":6.55,"name":"Sciurus"},{"decimalLatitude":53,"decimalLongitude":6.85,"name":"Capreolus"},{"decimalLatitude":52.6,"decimalLongitude":4.9,"name":"Lepus"},{"decimalLatitude":51.7,"decimalLongitude":4.65,"name":"Castor"},{"decimalLatitude":52.05,"decimalLongitude":4.3,"name":"Sciurus"},{"decimalLatitude":50.75,"decimalLongitude":5.95,"name":"Oryctolagus"},{"decimalLatitude":50.75,"decimalLongitude":5.95,"name":"Capreolus"},{"decimalLatitude":52.2,"decimalLongitude":4.4,"name":"Phoca"},{"decimalLatitude":51.25,"decimalLongitude":3.8,"name":"Capreolus"},{"decimalLatitude":51.4,"decimalLongitude":3.55,"name":"Phocoena"},{"decimalLatitude":53.1,"decimalLongitude":6.2,"name":"Capreolus"},{"decimalLatitude":51.85,"decimalLongitude":5.2,"name":"Capreolus"},{"decimalLatitude":53.15,"decimalLongitude":6.55,"name":"Sciurus"},{"decimalLatitude":52.45,"decimalLongitude":4.5,"name":"Halichoerus"},{"decimalLatitude":53.2,"decimalLongitude":6.5,"name":"Sciurus"},{"decimalLatitude":52.95,"decimalLongitude":4.7,"name":"Felis"},{"decimalLatitude":52.45,"decimalLongitude":4.55,"name":"Phoca"},{"decimalLatitude":51.8,"decimalLongitude":4.5,"name":"Castor"},{"decimalLatitude":51.95,"decimalLongitude":5.95,"name":"Oryctolagus"},{"decimalLatitude":53.05,"decimalLongitude":7.15,"name":"Capreolus"},{"decimalLatitude":52.4,"decimalLongitude":5.25,"name":"Bos"},{"decimalLatitude":52.4,"decimalLongitude":5.4,"name":"Vulpes"},{"decimalLatitude":51.55,"decimalLongitude":4.55,"name":"Oryctolagus"},{"decimalLatitude":53,"decimalLongitude":6.75,"name":"Capreolus"},{"decimalLatitude":53,"decimalLongitude":4.75,"name":"Felis"},{"decimalLatitude":52,"decimalLongitude":4.45,"name":"Lepus"},{"decimalLatitude":51.75,"decimalLongitude":5.75,"name":"Meles"},{"decimalLatitude":51.85,"decimalLongitude":4.25,"name":"Oryctolagus"},{"decimalLatitude":53.2,"decimalLongitude":6.65,"name":"Capreolus"},{"decimalLatitude":52.35,"decimalLongitude":5.3,"name":"Capreolus"},{"decimalLatitude":51.8,"decimalLongitude":5.9,"name":"Mustela"},{"decimalLatitude":51.85,"decimalLongitude":4.2,"name":"Oryctolagus"},{"decimalLatitude":51.9,"decimalLongitude":4,"name":"Oryctolagus"},{"decimalLatitude":51.9,"decimalLongitude":4.15,"name":"Oryctolagus"},{"decimalLatitude":51.9,"decimalLongitude":4.1,"name":"Oryctolagus"},{"decimalLatitude":53.2,"decimalLongitude":4.8,"name":"Halichoerus"},{"decimalLatitude":53.2,"decimalLongitude":7.15,"name":"Lepus"},{"decimalLatitude":52.3,"decimalLongitude":4.55,"name":"Vulpes"},{"decimalLatitude":50.8,"decimalLongitude":5.85,"name":"Vulpes"},{"decimalLatitude":52.55,"decimalLongitude":5,"name":"Lepus"},{"decimalLatitude":51.7,"decimalLongitude":4.4,"name":"Rattus"},{"decimalLatitude":51.15,"decimalLongitude":6.1,"name":"Sus"},{"decimalLatitude":52.4,"decimalLongitude":5.35,"name":"Equus"},{"decimalLatitude":51.9,"decimalLongitude":4.65,"name":"Lepus"},{"decimalLatitude":52.35,"decimalLongitude":5.15,"name":"Vulpes"},{"decimalLatitude":52.5,"decimalLongitude":6.05,"name":"Rattus"},{"decimalLatitude":52.45,"decimalLongitude":5.4,"name":"Capreolus"},{"decimalLatitude":51.4,"decimalLongitude":5.25,"name":"Capreolus"},{"decimalLatitude":53.4,"decimalLongitude":5.4,"name":"Felis"},{"decimalLatitude":51.95,"decimalLongitude":6,"name":"Capreolus"},{"decimalLatitude":52.15,"decimalLongitude":4.35,"name":"Capreolus"},{"decimalLatitude":52.15,"decimalLongitude":5.6,"name":"Lepus"},{"decimalLatitude":51.7,"decimalLongitude":4.75,"name":"Capreolus"},{"decimalLatitude":51.7,"decimalLongitude":3.8,"name":"Phoca"},{"decimalLatitude":52,"decimalLongitude":6.7,"name":"Lepus"},{"decimalLatitude":51.9,"decimalLongitude":4.25,"name":"Oryctolagus"},{"decimalLatitude":51.6,"decimalLongitude":5.45,"name":"Capreolus"},{"decimalLatitude":52.95,"decimalLongitude":6,"name":"Capreolus"},{"decimalLatitude":53.35,"decimalLongitude":6.45,"name":"Talpa"},{"decimalLatitude":51.25,"decimalLongitude":3.95,"name":"Vulpes"},{"decimalLatitude":51.7,"decimalLongitude":4.7,"name":"Talpa"},{"decimalLatitude":51.15,"decimalLongitude":6.1,"name":"Sus"},{"decimalLatitude":52.35,"decimalLongitude":5.3,"name":"Capreolus"},{"decimalLatitude":51.7,"decimalLongitude":5.75,"name":"Lepus"},{"decimalLatitude":51.6,"decimalLongitude":4.6,"name":"Lepus"},{"decimalLatitude":51.35,"decimalLongitude":4,"name":"Phoca"},{"decimalLatitude":51.45,"decimalLongitude":3.5,"name":"Capreolus"},{"decimalLatitude":52.4,"decimalLongitude":5.55,"name":"Lutra"},{"decimalLatitude":51.65,"decimalLongitude":4.85,"name":"Capreolus"},{"decimalLatitude":51.65,"decimalLongitude":5.2,"name":"Capreolus"},{"decimalLatitude":51.7,"decimalLongitude":5.75,"name":"Capreolus"},{"decimalLatitude":52.2,"decimalLongitude":6.6,"name":"Lepus"},{"decimalLatitude":52.45,"decimalLongitude":4.5,"name":"Phoca"},{"decimalLatitude":51.25,"decimalLongitude":3.95,"name":"Capreolus"},{"decimalLatitude":52.45,"decimalLongitude":4.55,"name":"Vulpes"},{"decimalLatitude":53.05,"decimalLongitude":4.75,"name":"Lepus"},{"decimalLatitude":51.8,"decimalLongitude":4,"name":"Capreolus"},{"decimalLatitude":52.35,"decimalLongitude":4.7,"name":"Lepus"},{"decimalLatitude":51.8,"decimalLongitude":5.95,"name":"Lutra"},{"decimalLatitude":52.45,"decimalLongitude":4.5,"name":"Phoca"},{"decimalLatitude":51.85,"decimalLongitude":4.2,"name":"Oryctolagus"},{"decimalLatitude":51.7,"decimalLongitude":3.8,"name":"Halichoerus"},{"decimalLatitude":51.55,"decimalLongitude":5.05,"name":"Mus"},{"decimalLatitude":52.4,"decimalLongitude":4.55,"name":"Oryctolagus"},{"decimalLatitude":51.75,"decimalLongitude":5.35,"name":"Lepus"},{"decimalLatitude":51.55,"decimalLongitude":5.95,"name":"Capreolus"},{"decimalLatitude":51.4,"decimalLongitude":3.55,"name":"Phoca"},{"decimalLatitude":52.2,"decimalLongitude":6.95,"name":"Oryctolagus"},{"decimalLatitude":52.8,"decimalLongitude":6.4,"name":"Capreolus"},{"decimalLatitude":51.8,"decimalLongitude":5.9,"name":"Felis"},{"decimalLatitude":51.8,"decimalLongitude":4.4,"name":"Myodes"},{"decimalLatitude":51.6,"decimalLongitude":3.7,"name":"Oryctolagus"},{"decimalLatitude":51.7,"decimalLongitude":4.35,"name":"Capreolus"},{"decimalLatitude":53.2,"decimalLongitude":5.85,"name":"Lutra"},{"decimalLatitude":53.2,"decimalLongitude":6.15,"name":"Talpa"},{"decimalLatitude":52.45,"decimalLongitude":5.4,"name":"Cervus"},{"decimalLatitude":51.95,"decimalLongitude":5.85,"name":"Vulpes"},{"decimalLatitude":51.9,"decimalLongitude":4.7,"name":"Lepus"},{"decimalLatitude":52.05,"decimalLongitude":5.85,"name":"Ovis"},{"decimalLatitude":52.6,"decimalLongitude":5,"name":"Lepus"},{"decimalLatitude":52.45,"decimalLongitude":4.5,"name":"Phoca"},{"decimalLatitude":53.3,"decimalLongitude":5.15,"name":"Halichoerus"},{"decimalLatitude":52.6,"decimalLongitude":6.05,"name":"Lepus"},{"decimalLatitude":51.3,"decimalLongitude":4.15,"name":"Vulpes"},{"decimalLatitude":51.75,"decimalLongitude":4.8,"name":"Capreolus"},{"decimalLatitude":52.1,"decimalLongitude":5.35,"name":"Capreolus"},{"decimalLatitude":51.9,"decimalLongitude":6.45,"name":"Talpa"},{"decimalLatitude":53.2,"decimalLongitude":7.15,"name":"Capreolus"},{"decimalLatitude":52.85,"decimalLongitude":6.35,"name":"Crocidura"},{"decimalLatitude":52.1,"decimalLongitude":6.3,"name":"Lepus"},{"decimalLatitude":52.4,"decimalLongitude":5.35,"name":"Capreolus"},{"decimalLatitude":51.5,"decimalLongitude":4.6,"name":"Sciurus"},{"decimalLatitude":51.75,"decimalLongitude":4.75,"name":"Capreolus"},{"decimalLatitude":52.3,"decimalLongitude":4.55,"name":"Dama"},{"decimalLatitude":55.3495,"decimalLongitude":11.8324,"name":"Capreolus"},{"decimalLatitude":55.5153,"decimalLongitude":9.6854,"name":"Sciurus"},{"decimalLatitude":55.7743,"decimalLongitude":12.3527,"name":"Sciurus"},{"decimalLatitude":55.8781,"decimalLongitude":9.8759,"name":"Capreolus"},{"decimalLatitude":55.5106,"decimalLongitude":9.5822,"name":"Dama"},{"decimalLatitude":54.8216,"decimalLongitude":9.2537,"name":"Cervus"},{"decimalLatitude":56.279,"decimalLongitude":10.8264,"name":"Phoca"},{"decimalLatitude":55.2039,"decimalLongitude":11.369,"name":"Capreolus"},{"decimalLatitude":56.1539,"decimalLongitude":10.1609,"name":"Felis"},{"decimalLatitude":55.8081,"decimalLongitude":12.5661,"name":"Sciurus"},{"decimalLatitude":55.4396,"decimalLongitude":12.198,"name":"Sciurus"},{"decimalLatitude":55.9212,"decimalLongitude":8.3893,"name":"Lepus"},{"decimalLatitude":55.8867,"decimalLongitude":11.9693,"name":"Capreolus"},{"decimalLatitude":55.9895,"decimalLongitude":12.5134,"name":"Capreolus"},{"decimalLatitude":55.442,"decimalLongitude":11.5582,"name":"Sciurus"},{"decimalLatitude":55.7262,"decimalLongitude":12.5665,"name":"Sciurus"},{"decimalLatitude":54.7925,"decimalLongitude":11.2491,"name":"Dama"},{"decimalLatitude":55.464,"decimalLongitude":11.8632,"name":"Capreolus"},{"decimalLatitude":54.8611,"decimalLongitude":10.7308,"name":"Dama"},{"decimalLatitude":55.1961,"decimalLongitude":10.4459,"name":"Capreolus"},{"decimalLatitude":59.6119,"decimalLongitude":8.9751,"name":"Lynx"},{"decimalLatitude":69.5976,"decimalLongitude":19.9687,"name":"Lynx"},{"decimalLatitude":62.1484,"decimalLongitude":7.4478,"name":"Gulo"},{"decimalLatitude":64.8464,"decimalLongitude":13.0343,"name":"Lynx"},{"decimalLatitude":60.9199,"decimalLongitude":9.3545,"name":"Lynx"},{"decimalLatitude":62.8237,"decimalLongitude":9.8962,"name":"Lynx"},{"decimalLatitude":12.5245,"decimalLongitude":2.7181,"name":"Tragelaphus"},{"decimalLatitude":12.4179,"decimalLongitude":2.7513,"name":"Civettictis"},{"decimalLatitude":63.5629,"decimalLongitude":11.9463,"name":"Sciurus"},{"decimalLatitude":58.3746,"decimalLongitude":8.6536,"name":"Sciurus"},{"decimalLatitude":59.5421,"decimalLongitude":10.2503,"name":"Sciurus"},{"decimalLatitude":60.6441,"decimalLongitude":10.3783,"name":"Alces"},{"decimalLatitude":63.2052,"decimalLongitude":10.2506,"name":"Sciurus"},{"decimalLatitude":63.0773,"decimalLongitude":7.6538,"name":"Felis"},{"decimalLatitude":59.0126,"decimalLongitude":11.5306,"name":"Sciurus"},{"decimalLatitude":67.9173,"decimalLongitude":15.1862,"name":"Sciurus"},{"decimalLatitude":61.3154,"decimalLongitude":7.2011,"name":"Vulpes"},{"decimalLatitude":63.4141,"decimalLongitude":11.743,"name":"Sciurus"},{"decimalLatitude":59.8713,"decimalLongitude":10.5007,"name":"Sciurus"},{"decimalLatitude":60.1351,"decimalLongitude":11.3981,"name":"Apodemus"},{"decimalLatitude":60.1843,"decimalLongitude":12.1716,"name":"Sciurus"},{"decimalLatitude":68.4071,"decimalLongitude":17.414,"name":"Vulpes"},{"decimalLatitude":59.7589,"decimalLongitude":10.0284,"name":"Sciurus"},{"decimalLatitude":60.1359,"decimalLongitude":11.2043,"name":"Sciurus"},{"decimalLatitude":63.1364,"decimalLongitude":8.5235,"name":"Felis"},{"decimalLatitude":68.616,"decimalLongitude":14.4758,"name":"Alces"},{"decimalLatitude":59.6114,"decimalLongitude":8.5141,"name":"Sciurus"},{"decimalLatitude":62.7479,"decimalLongitude":7.1895,"name":"Capreolus"},{"decimalLatitude":59.9517,"decimalLongitude":6.594,"name":"Sciurus"},{"decimalLatitude":59.2688,"decimalLongitude":10.7648,"name":"Felis"},{"decimalLatitude":62.2125,"decimalLongitude":9.7655,"name":"Sciurus"},{"decimalLatitude":60.1948,"decimalLongitude":9.2435,"name":"Sciurus"},{"decimalLatitude":63.5378,"decimalLongitude":10.0886,"name":"Alces"},{"decimalLatitude":61.766,"decimalLongitude":5.2571,"name":"Sciurus"},{"decimalLatitude":63.3947,"decimalLongitude":11.801,"name":"Capreolus"},{"decimalLatitude":62.5909,"decimalLongitude":9.6995,"name":"Sciurus"},{"decimalLatitude":63.3532,"decimalLongitude":10.2507,"name":"Sciurus"},{"decimalLatitude":66.3105,"decimalLongitude":14.2651,"name":"Sciurus"},{"decimalLatitude":59.669,"decimalLongitude":9.6699,"name":"Sciurus"},{"decimalLatitude":58.4655,"decimalLongitude":8.8251,"name":"Sciurus"},{"decimalLatitude":59.9302,"decimalLongitude":11.3486,"name":"Sciurus"},{"decimalLatitude":59.6827,"decimalLongitude":10.509,"name":"Capreolus"},{"decimalLatitude":58.6349,"decimalLongitude":6.5619,"name":"Sciurus"},{"decimalLatitude":67.2723,"decimalLongitude":14.7306,"name":"Alces"},{"decimalLatitude":60.8667,"decimalLongitude":11.5862,"name":"Sciurus"},{"decimalLatitude":61.6794,"decimalLongitude":6.8163,"name":"Sciurus"},{"decimalLatitude":59.2451,"decimalLongitude":9.5874,"name":"Sciurus"},{"decimalLatitude":59.4219,"decimalLongitude":9.0559,"name":"Sciurus"},{"decimalLatitude":58.7288,"decimalLongitude":5.6529,"name":"Felis"},{"decimalLatitude":59.2971,"decimalLongitude":9.1072,"name":"Capreolus"},{"decimalLatitude":59.789,"decimalLongitude":10.4825,"name":"Capreolus"},{"decimalLatitude":65.9755,"decimalLongitude":13.8331,"name":"Sciurus"},{"decimalLatitude":58.2421,"decimalLongitude":7.3639,"name":"Sciurus"},{"decimalLatitude":66.0275,"decimalLongitude":13.849,"name":"Sciurus"},{"decimalLatitude":61.2682,"decimalLongitude":10.1527,"name":"Sciurus"},{"decimalLatitude":60.178,"decimalLongitude":10.2322,"name":"Capreolus"},{"decimalLatitude":69.2401,"decimalLongitude":19.4588,"name":"Myodes"},{"decimalLatitude":61.2385,"decimalLongitude":7.7003,"name":"Sciurus"},{"decimalLatitude":63.5115,"decimalLongitude":10.0214,"name":"Felis"},{"decimalLatitude":59.0864,"decimalLongitude":10.2944,"name":"Sciurus"},{"decimalLatitude":59.503,"decimalLongitude":11.3761,"name":"Felis"},{"decimalLatitude":60.1602,"decimalLongitude":12.0321,"name":"Sciurus"},{"decimalLatitude":60.2296,"decimalLongitude":12.0863,"name":"Sciurus"},{"decimalLatitude":62.2513,"decimalLongitude":5.8377,"name":"Apodemus"},{"decimalLatitude":60.9958,"decimalLongitude":10.4305,"name":"Sciurus"},{"decimalLatitude":63.2289,"decimalLongitude":9.4164,"name":"Sciurus"},{"decimalLatitude":59.9384,"decimalLongitude":10.9918,"name":"Capreolus"},{"decimalLatitude":59.8337,"decimalLongitude":10.8619,"name":"Sciurus"},{"decimalLatitude":59.112,"decimalLongitude":9.6668,"name":"Sciurus"},{"decimalLatitude":60.0646,"decimalLongitude":10.3172,"name":"Sciurus"},{"decimalLatitude":60.0501,"decimalLongitude":10.895,"name":"Capreolus"},{"decimalLatitude":59.7727,"decimalLongitude":10.415,"name":"Capreolus"},{"decimalLatitude":59.843,"decimalLongitude":10.4458,"name":"Sciurus"},{"decimalLatitude":59.5461,"decimalLongitude":10.7058,"name":"Capreolus"},{"decimalLatitude":64.2425,"decimalLongitude":11.6166,"name":"Gulo"},{"decimalLatitude":63.2557,"decimalLongitude":10.4382,"name":"Alces"},{"decimalLatitude":64.812,"decimalLongitude":13.4209,"name":"Lynx"},{"decimalLatitude":63.7532,"decimalLongitude":11.5773,"name":"Felis"},{"decimalLatitude":60.1359,"decimalLongitude":11.0115,"name":"Sciurus"},{"decimalLatitude":60.2102,"decimalLongitude":10.6814,"name":"Felis"},{"decimalLatitude":62.8515,"decimalLongitude":8.5225,"name":"Sciurus"},{"decimalLatitude":61.4455,"decimalLongitude":11.366,"name":"Canis"},{"decimalLatitude":61.261,"decimalLongitude":27.8355,"name":"Felis"},{"decimalLatitude":60.189,"decimalLongitude":25.0022,"name":"Sciurus"},{"decimalLatitude":60.0636,"decimalLongitude":24.0337,"name":"Sciurus"},{"decimalLatitude":60.8976,"decimalLongitude":28.3788,"name":"Sciurus"},{"decimalLatitude":61.6723,"decimalLongitude":23.6915,"name":"Sciurus"},{"decimalLatitude":61.6723,"decimalLongitude":23.6915,"name":"Sciurus"},{"decimalLatitude":60.6236,"decimalLongitude":21.7875,"name":"Capreolus"},{"decimalLatitude":44.3408,"decimalLongitude":-72.4613,"name":"Canis"},{"decimalLatitude":51.55,"decimalLongitude":3.55,"name":"Dama"},{"decimalLatitude":38.9167,"decimalLongitude":-76.949,"name":"Procyon"},{"decimalLatitude":32.904,"decimalLongitude":35.9889,"name":"Gazella"},{"decimalLatitude":-0.7828,"decimalLongitude":-76.2159,"name":"Tapirus"},{"decimalLatitude":58.0908,"decimalLongitude":7.8299,"name":"Neovison"},{"decimalLatitude":59.3894,"decimalLongitude":5.2929,"name":"Neovison"},{"decimalLatitude":-52.5626,"decimalLongitude":169.1362,"name":"Mirounga"},{"decimalLatitude":3.5922,"decimalLongitude":-75.9328,"name":"Tapirus"},{"decimalLatitude":3.5736,"decimalLongitude":-75.9574,"name":"Tapirus"},{"decimalLatitude":63.2495,"decimalLongitude":10.4387,"name":"Sciurus"},{"decimalLatitude":59.8833,"decimalLongitude":10.8333,"name":"Rattus"},{"decimalLatitude":59.8459,"decimalLongitude":10.5589,"name":"Phoca"},{"decimalLatitude":63.2495,"decimalLongitude":10.4387,"name":"Vulpes"},{"decimalLatitude":59.87,"decimalLongitude":10.6635,"name":"Phoca"},{"decimalLatitude":59.4236,"decimalLongitude":5.3064,"name":"Sciurus"},{"decimalLatitude":63.346,"decimalLongitude":10.3273,"name":"Capreolus"},{"decimalLatitude":63.3118,"decimalLongitude":9.1839,"name":"Sciurus"},{"decimalLatitude":63.3479,"decimalLongitude":10.8751,"name":"Capreolus"},{"decimalLatitude":50.9882,"decimalLongitude":5.4717,"name":"Oryctolagus"},{"decimalLatitude":51.0951,"decimalLongitude":4.1922,"name":"Rattus"},{"decimalLatitude":51.0952,"decimalLongitude":4.1922,"name":"Rattus"},{"decimalLatitude":50.9867,"decimalLongitude":5.0138,"name":"Felis"},{"decimalLatitude":50.9397,"decimalLongitude":5.3653,"name":"Oryctolagus"},{"decimalLatitude":51.0354,"decimalLongitude":4.2558,"name":"Oryctolagus"},{"decimalLatitude":50.9113,"decimalLongitude":3.861,"name":"Oryctolagus"},{"decimalLatitude":50.7949,"decimalLongitude":2.7717,"name":"Oryctolagus"},{"decimalLatitude":51.1852,"decimalLongitude":4.4779,"name":"Oryctolagus"},{"decimalLatitude":36.1273,"decimalLongitude":-5.2531,"name":"Macaca"},{"decimalLatitude":55.5739,"decimalLongitude":11.2603,"name":"Capreolus"},{"decimalLatitude":-3.1478,"decimalLongitude":-59.9392,"name":"Cebus"},{"decimalLatitude":48.3004,"decimalLongitude":-123.532,"name":"Mirounga"},{"decimalLatitude":65.6726,"decimalLongitude":21.1612,"name":"Lutra"},{"decimalLatitude":67.1845,"decimalLongitude":20.7783,"name":"Rangifer"},{"decimalLatitude":60.0184,"decimalLongitude":17.7309,"name":"Lutra"},{"decimalLatitude":13.726,"decimalLongitude":-15.3438,"name":"Heliosciurus"},{"decimalLatitude":52.9225,"decimalLongitude":8.6162,"name":"Capreolus"},{"decimalLatitude":51.399,"decimalLongitude":9.7867,"name":"Capreolus"},{"decimalLatitude":50.705,"decimalLongitude":6.6277,"name":"Capreolus"},{"decimalLatitude":50.8866,"decimalLongitude":12.8925,"name":"Castor"},{"decimalLatitude":52.0028,"decimalLongitude":9.8602,"name":"Capreolus"},{"decimalLatitude":49.9343,"decimalLongitude":8.3242,"name":"Capreolus"},{"decimalLatitude":50.9463,"decimalLongitude":6.2689,"name":"Castor"},{"decimalLatitude":57.4149,"decimalLongitude":15.1161,"name":"Neovison"},{"decimalLatitude":47.9445,"decimalLongitude":9.7572,"name":"Martes"},{"decimalLatitude":50.1544,"decimalLongitude":8.6466,"name":"Myocastor"},{"decimalLatitude":50.1426,"decimalLongitude":10.7295,"name":"Oryctolagus"},{"decimalLatitude":59.8275,"decimalLongitude":17.6649,"name":"Lutra"},{"decimalLatitude":52.9539,"decimalLongitude":10.5617,"name":"Sciurus"},{"decimalLatitude":51.3511,"decimalLongitude":7.4502,"name":"Sciurus"},{"decimalLatitude":47.8042,"decimalLongitude":9.649,"name":"Sciurus"},{"decimalLatitude":50.8564,"decimalLongitude":6.1569,"name":"Sciurus"},{"decimalLatitude":49.6861,"decimalLongitude":8.9773,"name":"Sus"},{"decimalLatitude":50.1351,"decimalLongitude":8.9585,"name":"Talpa"},{"decimalLatitude":52.4376,"decimalLongitude":13.5176,"name":"Vulpes"},{"decimalLatitude":51.6469,"decimalLongitude":12.3916,"name":"Vulpes"},{"decimalLatitude":48.8843,"decimalLongitude":10.3603,"name":"Bos"},{"decimalLatitude":53.6655,"decimalLongitude":8.497,"name":"Capreolus"},{"decimalLatitude":-43.6312,"decimalLongitude":172.5611,"name":"Oryctolagus"},{"decimalLatitude":59.9458,"decimalLongitude":8.8199,"name":"Lynx"},{"decimalLatitude":59.9763,"decimalLongitude":10.3157,"name":"Lynx"},{"decimalLatitude":59.9923,"decimalLongitude":11.454,"name":"Canis"},{"decimalLatitude":60.7573,"decimalLongitude":11.7113,"name":"Lynx"},{"decimalLatitude":11.5298,"decimalLongitude":1.3747,"name":"Ichneumia"},{"decimalLatitude":41.2282,"decimalLongitude":-111.9107,"name":"Alces"},{"decimalLatitude":44.4307,"decimalLongitude":-73.151,"name":"Lynx"},{"decimalLatitude":60.8284,"decimalLongitude":21.56,"name":"Sciurus"},{"decimalLatitude":60.2123,"decimalLongitude":25.0163,"name":"Sciurus"},{"decimalLatitude":60.236,"decimalLongitude":25.1618,"name":"Sciurus"},{"decimalLatitude":61.435,"decimalLongitude":21.8401,"name":"Sciurus"},{"decimalLatitude":61.394,"decimalLongitude":23.3464,"name":"Sciurus"},{"decimalLatitude":60.7952,"decimalLongitude":24.7012,"name":"Lepus"},{"decimalLatitude":61.435,"decimalLongitude":21.8401,"name":"Lepus"},{"decimalLatitude":62.1609,"decimalLongitude":27.0928,"name":"Sciurus"},{"decimalLatitude":60.6943,"decimalLongitude":21.7473,"name":"Capreolus"},{"decimalLatitude":60.0677,"decimalLongitude":24.4624,"name":"Capreolus"},{"decimalLatitude":59.905,"decimalLongitude":23.1164,"name":"Capreolus"},{"decimalLatitude":60.4685,"decimalLongitude":22.319,"name":"Myodes"},{"decimalLatitude":-46.771,"decimalLongitude":168.8918,"name":"Phocarctos"},{"decimalLatitude":55.8595,"decimalLongitude":10.154,"name":"Capreolus"},{"decimalLatitude":55.4421,"decimalLongitude":11.5583,"name":"Sciurus"},{"decimalLatitude":55.8689,"decimalLongitude":10.0027,"name":"Vulpes"},{"decimalLatitude":54.9978,"decimalLongitude":8.9284,"name":"Capreolus"},{"decimalLatitude":54.9054,"decimalLongitude":8.8526,"name":"Capreolus"},{"decimalLatitude":57.1942,"decimalLongitude":9.8142,"name":"Vulpes"},{"decimalLatitude":55.2233,"decimalLongitude":11.3461,"name":"Capreolus"},{"decimalLatitude":56.2089,"decimalLongitude":10.1138,"name":"Capreolus"},{"decimalLatitude":55.5613,"decimalLongitude":11.2564,"name":"Capreolus"},{"decimalLatitude":55.0596,"decimalLongitude":12.0135,"name":"Capreolus"},{"decimalLatitude":56.1272,"decimalLongitude":9.9892,"name":"Sciurus"},{"decimalLatitude":56.1272,"decimalLongitude":9.9892,"name":"Capreolus"},{"decimalLatitude":55.4224,"decimalLongitude":12.1202,"name":"Capreolus"},{"decimalLatitude":55.9586,"decimalLongitude":12.5282,"name":"Capreolus"},{"decimalLatitude":57.7446,"decimalLongitude":10.6451,"name":"Phocoena"},{"decimalLatitude":55.9503,"decimalLongitude":11.5185,"name":"Lepus"},{"decimalLatitude":56.013,"decimalLongitude":12.3318,"name":"Sciurus"},{"decimalLatitude":55.7563,"decimalLongitude":12.0011,"name":"Capreolus"},{"decimalLatitude":55.3128,"decimalLongitude":11.8288,"name":"Capreolus"},{"decimalLatitude":52.2,"decimalLongitude":4.4,"name":"Phocoena"},{"decimalLatitude":50.8,"decimalLongitude":5.65,"name":"Apodemus"},{"decimalLatitude":51.8,"decimalLongitude":4.7,"name":"Capreolus"},{"decimalLatitude":52.8,"decimalLongitude":5.9,"name":"Lutra"},{"decimalLatitude":51.65,"decimalLongitude":3.75,"name":"Capreolus"},{"decimalLatitude":52.15,"decimalLongitude":6.85,"name":"Capreolus"},{"decimalLatitude":51.7,"decimalLongitude":3.65,"name":"Dama"},{"decimalLatitude":52.35,"decimalLongitude":4.55,"name":"Vulpes"},{"decimalLatitude":52,"decimalLongitude":5.3,"name":"Capreolus"},{"decimalLatitude":52.65,"decimalLongitude":4.6,"name":"Oryctolagus"},{"decimalLatitude":51.6,"decimalLongitude":3.7,"name":"Halichoerus"},{"decimalLatitude":52.3,"decimalLongitude":4.55,"name":"Capreolus"},{"decimalLatitude":51.95,"decimalLongitude":5.6,"name":"Capreolus"},{"decimalLatitude":52.5,"decimalLongitude":6.15,"name":"Lutra"},{"decimalLatitude":52.05,"decimalLongitude":5.55,"name":"Capreolus"},{"decimalLatitude":51.9,"decimalLongitude":4.6,"name":"Lepus"},{"decimalLatitude":53.35,"decimalLongitude":6.85,"name":"Capreolus"},{"decimalLatitude":52,"decimalLongitude":4.25,"name":"Lepus"},{"decimalLatitude":50.75,"decimalLongitude":5.75,"name":"Meles"},{"decimalLatitude":51.5,"decimalLongitude":3.65,"name":"Lepus"},{"decimalLatitude":53,"decimalLongitude":6.8,"name":"Capreolus"},{"decimalLatitude":52.25,"decimalLongitude":6.15,"name":"Sciurus"},{"decimalLatitude":52.45,"decimalLongitude":4.5,"name":"Phoca"},{"decimalLatitude":52.15,"decimalLongitude":5.2,"name":"Lepus"},{"decimalLatitude":52.4,"decimalLongitude":4.6,"name":"Dama"},{"decimalLatitude":51.9,"decimalLongitude":4.7,"name":"Talpa"},{"decimalLatitude":51.85,"decimalLongitude":5.2,"name":"Capreolus"},{"decimalLatitude":51.9,"decimalLongitude":4,"name":"Oryctolagus"},{"decimalLatitude":52.7,"decimalLongitude":4.8,"name":"Lepus"},{"decimalLatitude":52.55,"decimalLongitude":4.65,"name":"Plecotus"},{"decimalLatitude":51.25,"decimalLongitude":5.85,"name":"Vulpes"},{"decimalLatitude":52.35,"decimalLongitude":4.55,"name":"Sciurus"},{"decimalLatitude":52.3,"decimalLongitude":5.3,"name":"Capreolus"},{"decimalLatitude":51.45,"decimalLongitude":5.9,"name":"Capreolus"},{"decimalLatitude":52.45,"decimalLongitude":4.5,"name":"Phocoena"},{"decimalLatitude":52.55,"decimalLongitude":4.65,"name":"Lepus"},{"decimalLatitude":52.95,"decimalLongitude":4.75,"name":"Phoca"},{"decimalLatitude":52.2,"decimalLongitude":6.25,"name":"Talpa"},{"decimalLatitude":51.75,"decimalLongitude":3.85,"name":"Halichoerus"},{"decimalLatitude":51.95,"decimalLongitude":5.2,"name":"Microtus"},{"decimalLatitude":51.9,"decimalLongitude":4.9,"name":"Lepus"},{"decimalLatitude":52.65,"decimalLongitude":6.6,"name":"Talpa"},{"decimalLatitude":53,"decimalLongitude":6.75,"name":"Capreolus"},{"decimalLatitude":51.8,"decimalLongitude":4.4,"name":"Lepus"},{"decimalLatitude":53.2,"decimalLongitude":5.8,"name":"Capreolus"},{"decimalLatitude":51.25,"decimalLongitude":3.85,"name":"Capreolus"},{"decimalLatitude":53.05,"decimalLongitude":6.7,"name":"Capreolus"},{"decimalLatitude":51.8,"decimalLongitude":4.45,"name":"Castor"},{"decimalLatitude":51.4,"decimalLongitude":4.35,"name":"Capreolus"},{"decimalLatitude":52.35,"decimalLongitude":4.7,"name":"Lepus"},{"decimalLatitude":51.3,"decimalLongitude":3.85,"name":"Capreolus"},{"decimalLatitude":51.8,"decimalLongitude":4.9,"name":"Capreolus"},{"decimalLatitude":52.4,"decimalLongitude":5.75,"name":"Vulpes"},{"decimalLatitude":51.8,"decimalLongitude":5.9,"name":"Lutra"},{"decimalLatitude":52.45,"decimalLongitude":5.4,"name":"Cervus"},{"decimalLatitude":53.4,"decimalLongitude":6.5,"name":"Lepus"},{"decimalLatitude":51.75,"decimalLongitude":4.25,"name":"Capreolus"},{"decimalLatitude":52,"decimalLongitude":5.7,"name":"Capreolus"},{"decimalLatitude":51.8,"decimalLongitude":5.7,"name":"Oryctolagus"},{"decimalLatitude":52.15,"decimalLongitude":5.35,"name":"Lepus"},{"decimalLatitude":52,"decimalLongitude":5.3,"name":"Sciurus"},{"decimalLatitude":51.75,"decimalLongitude":5.75,"name":"Capreolus"},{"decimalLatitude":52.45,"decimalLongitude":4.5,"name":"Phoca"},{"decimalLatitude":52.15,"decimalLongitude":5.7,"name":"Sus"},{"decimalLatitude":52.45,"decimalLongitude":4.5,"name":"Phoca"},{"decimalLatitude":53.25,"decimalLongitude":6.8,"name":"Lepus"},{"decimalLatitude":51.6,"decimalLongitude":4.85,"name":"Capreolus"},{"decimalLatitude":52.3,"decimalLongitude":4.8,"name":"Oryctolagus"},{"decimalLatitude":52.45,"decimalLongitude":4.55,"name":"Halichoerus"},{"decimalLatitude":53.1,"decimalLongitude":6.45,"name":"Capreolus"},{"decimalLatitude":52.8,"decimalLongitude":7,"name":"Talpa"},{"decimalLatitude":53.15,"decimalLongitude":6.45,"name":"Neomys"},{"decimalLatitude":51.9,"decimalLongitude":5.2,"name":"Capreolus"},{"decimalLatitude":51.95,"decimalLongitude":5.6,"name":"Lepus"},{"decimalLatitude":53.15,"decimalLongitude":6.45,"name":"Capreolus"},{"decimalLatitude":51.75,"decimalLongitude":4,"name":"Capreolus"},{"decimalLatitude":52.3,"decimalLongitude":4.9,"name":"Oryctolagus"},{"decimalLatitude":51.75,"decimalLongitude":3.85,"name":"Phoca"},{"decimalLatitude":51.35,"decimalLongitude":5.8,"name":"Sus"},{"decimalLatitude":51.6,"decimalLongitude":6.05,"name":"Capreolus"},{"decimalLatitude":51.8,"decimalLongitude":5.6,"name":"Lepus"},{"decimalLatitude":51.65,"decimalLongitude":3.7,"name":"Capreolus"},{"decimalLatitude":51.55,"decimalLongitude":5.3,"name":"Capreolus"},{"decimalLatitude":52.2,"decimalLongitude":6.95,"name":"Capreolus"},{"decimalLatitude":51.7,"decimalLongitude":3.8,"name":"Halichoerus"},{"decimalLatitude":51.7,"decimalLongitude":3.8,"name":"Phoca"},{"decimalLatitude":51.8,"decimalLongitude":4.4,"name":"Lepus"},{"decimalLatitude":51.8,"decimalLongitude":4.4,"name":"Lepus"},{"decimalLatitude":53.35,"decimalLongitude":5.2,"name":"Halichoerus"},{"decimalLatitude":51.65,"decimalLongitude":5,"name":"Lepus"},{"decimalLatitude":51.75,"decimalLongitude":4.7,"name":"Lepus"},{"decimalLatitude":53.4,"decimalLongitude":5.3,"name":"Myodes"},{"decimalLatitude":50.8,"decimalLongitude":5.9,"name":"Meles"},{"decimalLatitude":51.15,"decimalLongitude":5.85,"name":"Castor"},{"decimalLatitude":51.25,"decimalLongitude":5.8,"name":"Capreolus"},{"decimalLatitude":52.2,"decimalLongitude":6.7,"name":"Talpa"},{"decimalLatitude":51.9,"decimalLongitude":6.45,"name":"Talpa"},{"decimalLatitude":51.7,"decimalLongitude":4.5,"name":"Dama"},{"decimalLatitude":51.85,"decimalLongitude":4.6,"name":"Erinaceus"},{"decimalLatitude":51.35,"decimalLongitude":6.1,"name":"Castor"},{"decimalLatitude":52.25,"decimalLongitude":4.95,"name":"Lepus"},{"decimalLatitude":52.2,"decimalLongitude":6.75,"name":"Talpa"},{"decimalLatitude":51.8,"decimalLongitude":4.4,"name":"Myodes"},{"decimalLatitude":51.8,"decimalLongitude":4.4,"name":"Myodes"},{"decimalLatitude":52.05,"decimalLongitude":5.6,"name":"Sciurus"},{"decimalLatitude":60.3768,"decimalLongitude":11.6047,"name":"Capreolus"},{"decimalLatitude":58.98,"decimalLongitude":24.09,"name":"Alces"},{"decimalLatitude":59.25,"decimalLongitude":24.88,"name":"Vulpes"},{"decimalLatitude":63.189,"decimalLongitude":14.61,"name":"Sciurus"},{"decimalLatitude":45.479,"decimalLongitude":-122.6414,"name":"Sciurus"},{"decimalLatitude":5.3489,"decimalLongitude":-72.4005,"name":"Tamandua"},{"decimalLatitude":53.09,"decimalLongitude":-3.27,"name":"Meles"},{"decimalLatitude":-35.681,"decimalLongitude":148.4871,"name":"Vulpes"},{"decimalLatitude":-32.3872,"decimalLongitude":150.8886,"name":"Oryctolagus"},{"decimalLatitude":-35.6038,"decimalLongitude":149.5138,"name":"Wallabia"},{"decimalLatitude":59.6655,"decimalLongitude":17.3827,"name":"Lutra"},{"decimalLatitude":63.2705,"decimalLongitude":13.6438,"name":"Alces"},{"decimalLatitude":58.9046,"decimalLongitude":17.4885,"name":"Ovis"},{"decimalLatitude":58.4973,"decimalLongitude":12.3255,"name":"Capreolus"},{"decimalLatitude":65.2763,"decimalLongitude":19.6857,"name":"Capreolus"},{"decimalLatitude":56.4769,"decimalLongitude":16.131,"name":"Capreolus"},{"decimalLatitude":62.1068,"decimalLongitude":16.6993,"name":"Capreolus"},{"decimalLatitude":59.8267,"decimalLongitude":17.6746,"name":"Vulpes"},{"decimalLatitude":57.9125,"decimalLongitude":15.7688,"name":"Lepus"},{"decimalLatitude":63.1332,"decimalLongitude":14.6519,"name":"Alces"},{"decimalLatitude":65.8204,"decimalLongitude":21.6023,"name":"Alces"},{"decimalLatitude":55.681,"decimalLongitude":13.428,"name":"Sus"},{"decimalLatitude":59.1935,"decimalLongitude":18.054,"name":"Capreolus"},{"decimalLatitude":55.3922,"decimalLongitude":12.8482,"name":"Sciurus"},{"decimalLatitude":65.83,"decimalLongitude":24.1358,"name":"Sciurus"},{"decimalLatitude":60.5589,"decimalLongitude":16.6131,"name":"Lutra"},{"decimalLatitude":63.9962,"decimalLongitude":19.6839,"name":"Sciurus"},{"decimalLatitude":58.3117,"decimalLongitude":12.0482,"name":"Alces"},{"decimalLatitude":60.6042,"decimalLongitude":17.9883,"name":"Lutra"},{"decimalLatitude":59.9132,"decimalLongitude":17.576,"name":"Lutra"},{"decimalLatitude":58.7976,"decimalLongitude":17.8004,"name":"Halichoerus"},{"decimalLatitude":57.7704,"decimalLongitude":11.9745,"name":"Sciurus"},{"decimalLatitude":59.3484,"decimalLongitude":17.895,"name":"Rattus"},{"decimalLatitude":62.5063,"decimalLongitude":6.0297,"name":"Phoca"},{"decimalLatitude":58.8242,"decimalLongitude":5.7493,"name":"Capreolus"},{"decimalLatitude":1.3447,"decimalLongitude":103.7831,"name":"Galeopterus"},{"decimalLatitude":30.3766,"decimalLongitude":-103.5364,"name":"Odocoileus"},{"decimalLatitude":-33.9425,"decimalLongitude":22.4612,"name":"Genetta"},{"decimalLatitude":-36.5815,"decimalLongitude":149.3853,"name":"Vulpes"},{"decimalLatitude":-32.7379,"decimalLongitude":152.0308,"name":"Phascolarctos"},{"decimalLatitude":-36.5982,"decimalLongitude":149.3758,"name":"Vombatus"},{"decimalLatitude":-32.6398,"decimalLongitude":152.164,"name":"Isoodon"},{"decimalLatitude":-36.5827,"decimalLongitude":149.3855,"name":"Dama"},{"decimalLatitude":-29.0725,"decimalLongitude":153.0343,"name":"Trichosurus"},{"decimalLatitude":6.8058,"decimalLongitude":-74.2134,"name":"Dasyprocta"},{"decimalLatitude":0.4589,"decimalLongitude":30.3704,"name":"Papio"},{"decimalLatitude":46.3167,"decimalLongitude":6.3149,"name":"Sus"},{"decimalLatitude":46.3167,"decimalLongitude":6.3149,"name":"Meles"},{"decimalLatitude":40.795,"decimalLongitude":-96.6382,"name":"Vulpes"},{"decimalLatitude":38.0723,"decimalLongitude":-76.6475,"name":"Sylvilagus"},{"decimalLatitude":52.8727,"decimalLongitude":0.9892,"name":"Pipistrellus"},{"decimalLatitude":50.51,"decimalLongitude":-4.07,"name":"Rhinolophus"},{"decimalLatitude":58.2651,"decimalLongitude":-6.1116,"name":"Lagenorhynchus"},{"decimalLatitude":57.6738,"decimalLongitude":-3.0934,"name":"Halichoerus"},{"decimalLatitude":56.4677,"decimalLongitude":-2.8577,"name":"Sciurus"},{"decimalLatitude":-12.1248,"decimalLongitude":-71.2325,"name":"Lagothrix"},{"decimalLatitude":11.3885,"decimalLongitude":76.683,"name":"Ratufa"},{"decimalLatitude":6.8058,"decimalLongitude":-74.2134,"name":"Eira"},{"decimalLatitude":-32.3939,"decimalLongitude":151.035,"name":"Osphranter"},{"decimalLatitude":-35.73,"decimalLongitude":148.4888,"name":"Trichosurus"},{"decimalLatitude":-32.9823,"decimalLongitude":151.5272,"name":"Pseudocheirus"},{"decimalLatitude":-35.6053,"decimalLongitude":149.5046,"name":"Macropus"},{"decimalLatitude":-35.6038,"decimalLongitude":149.5112,"name":"Petauroides"},{"decimalLatitude":-32.667,"decimalLongitude":152.0791,"name":"Macropus"},{"decimalLatitude":-35.7805,"decimalLongitude":150.1641,"name":"Petaurus"},{"decimalLatitude":-34.1035,"decimalLongitude":150.81,"name":"Phascolarctos"},{"decimalLatitude":-31.3858,"decimalLongitude":151.8746,"name":"Chalinolobus"},{"decimalLatitude":-29.7848,"decimalLongitude":153.2015,"name":"Petaurus"},{"decimalLatitude":-35.4176,"decimalLongitude":150.2687,"name":"Vombatus"},{"decimalLatitude":-36.6233,"decimalLongitude":149.3826,"name":"Pseudocheirus"},{"decimalLatitude":-35.9929,"decimalLongitude":148.4573,"name":"Vombatus"},{"decimalLatitude":-35.7317,"decimalLongitude":148.4858,"name":"Rattus"},{"decimalLatitude":-31.6558,"decimalLongitude":152.4726,"name":"Potorous"},{"decimalLatitude":-30.7032,"decimalLongitude":152.7219,"name":"Petaurus"},{"decimalLatitude":-32.9391,"decimalLongitude":151.5727,"name":"Pseudocheirus"},{"decimalLatitude":-33.8897,"decimalLongitude":150.9606,"name":"Trichosurus"},{"decimalLatitude":-32.2062,"decimalLongitude":152.5038,"name":"Petaurus"},{"decimalLatitude":53.2481,"decimalLongitude":51.2725,"name":"Castor"},{"decimalLatitude":56.6944,"decimalLongitude":38.6444,"name":"Castor"},{"decimalLatitude":56.4919,"decimalLongitude":38.413,"name":"Castor"},{"decimalLatitude":63.0149,"decimalLongitude":8.6923,"name":"Lepus"},{"decimalLatitude":52.0095,"decimalLongitude":0.4774,"name":"Lepus"},{"decimalLatitude":50.85,"decimalLongitude":0.49,"name":"Meles"},{"decimalLatitude":53.1799,"decimalLongitude":-2.7814,"name":"Talpa"},{"decimalLatitude":57.4594,"decimalLongitude":-4.2267,"name":"Sciurus"},{"decimalLatitude":53.1927,"decimalLongitude":-2.8893,"name":"Sciurus"},{"decimalLatitude":54.9219,"decimalLongitude":-2.8527,"name":"Sciurus"},{"decimalLatitude":55.9053,"decimalLongitude":-3.0332,"name":"Vulpes"},{"decimalLatitude":53.1976,"decimalLongitude":-2.5086,"name":"Vulpes"},{"decimalLatitude":54.2387,"decimalLongitude":-2.766,"name":"Capreolus"},{"decimalLatitude":51.935,"decimalLongitude":0.2166,"name":"Dama"},{"decimalLatitude":56.2833,"decimalLongitude":-3.1159,"name":"Sciurus"},{"decimalLatitude":53.1399,"decimalLongitude":-1.4431,"name":"Myodes"},{"decimalLatitude":51.3254,"decimalLongitude":0.6615,"name":"Oryctolagus"},{"decimalLatitude":50.811,"decimalLongitude":-0.0292,"name":"Vulpes"},{"decimalLatitude":6.8053,"decimalLongitude":-74.2109,"name":"Cuniculus"},{"decimalLatitude":34.3182,"decimalLongitude":-86.4958,"name":"Mephitis"},{"decimalLatitude":-23.9884,"decimalLongitude":31.5547,"name":"Tragelaphus"},{"decimalLatitude":42.328,"decimalLongitude":-72.543,"name":"Sciurus"},{"decimalLatitude":-12.2001,"decimalLongitude":-71.0063,"name":"Saimiri"},{"decimalLatitude":29.31,"decimalLongitude":-82.43,"name":"Teleoceras"},{"decimalLatitude":-27.2175,"decimalLongitude":153.0251,"name":"Phascolarctos"},{"decimalLatitude":12.4485,"decimalLongitude":2.385,"name":"Tragelaphus"},{"decimalLatitude":59.0044,"decimalLongitude":9.7388,"name":"Sciurus"},{"decimalLatitude":58.1601,"decimalLongitude":8.0883,"name":"Sciurus"},{"decimalLatitude":59.9039,"decimalLongitude":10.8528,"name":"Sciurus"},{"decimalLatitude":59.3889,"decimalLongitude":9.2922,"name":"Sciurus"},{"decimalLatitude":60.7134,"decimalLongitude":11.1174,"name":"Capreolus"},{"decimalLatitude":60.2709,"decimalLongitude":5.3255,"name":"Sciurus"},{"decimalLatitude":59.857,"decimalLongitude":10.8217,"name":"Sciurus"},{"decimalLatitude":51.716,"decimalLongitude":5.4048,"name":"Myotis"},{"decimalLatitude":-0.6332,"decimalLongitude":30.8816,"name":"Hippopotamus"},{"decimalLatitude":-37.8379,"decimalLongitude":145.398,"name":"Tachyglossus"},{"decimalLatitude":45.5569,"decimalLongitude":-64.9089,"name":"Lynx"},{"decimalLatitude":30.084,"decimalLongitude":-95.695,"name":"Sciurus"},{"decimalLatitude":-27.7248,"decimalLongitude":153.3293,"name":"Macropus"},{"decimalLatitude":19.6241,"decimalLongitude":-101.0976,"name":"Nasua"},{"decimalLatitude":45.7958,"decimalLongitude":-122.7634,"name":"Lontra"},{"decimalLatitude":28.6311,"decimalLongitude":-82.5832,"name":"Dasypus"},{"decimalLatitude":38.9946,"decimalLongitude":-75.3643,"name":"Sciurus"},{"decimalLatitude":33.8267,"decimalLongitude":-116.1445,"name":"Ovis"},{"decimalLatitude":32.9274,"decimalLongitude":-117.0808,"name":"Sylvilagus"},{"decimalLatitude":-33.4,"decimalLongitude":151.5,"name":"Mammalia"},{"decimalLatitude":-38.5023,"decimalLongitude":145.1539,"name":"Wallabia"},{"decimalLatitude":39.9578,"decimalLongitude":-105.1563,"name":"Canis"},{"decimalLatitude":48.4184,"decimalLongitude":-123.3005,"name":"Odocoileus"},{"decimalLatitude":44.4831,"decimalLongitude":-77.2959,"name":"Tamiasciurus"},{"decimalLatitude":32.7112,"decimalLongitude":-95.1836,"name":"Castor"},{"decimalLatitude":32.2817,"decimalLongitude":-111.024,"name":"Canis"},{"decimalLatitude":37.1622,"decimalLongitude":-122.3626,"name":"Mirounga"},{"decimalLatitude":33.0556,"decimalLongitude":-100.516,"name":"Procyon"},{"decimalLatitude":25.2909,"decimalLongitude":-100.8988,"name":"Ursus"},{"decimalLatitude":29.1341,"decimalLongitude":-83.0313,"name":"Tursiops"},{"decimalLatitude":11.5403,"decimalLongitude":1.5597,"name":"Hippopotamus"},{"decimalLatitude":-23.5827,"decimalLongitude":31.5542,"name":"Damaliscus"},{"decimalLatitude":11.2192,"decimalLongitude":1.5469,"name":"Panthera"},{"decimalLatitude":57.0451,"decimalLongitude":-135.3147,"name":"Tamiasciurus"},{"decimalLatitude":44.3279,"decimalLongitude":-80.9388,"name":"Odocoileus"},{"decimalLatitude":33.4106,"decimalLongitude":-97.5894,"name":"Dasypus"},{"decimalLatitude":-28.3153,"decimalLongitude":32.4323,"name":"Connochaetes"},{"decimalLatitude":42.3555,"decimalLongitude":-71.0667,"name":"Sciurus"},{"decimalLatitude":28.9885,"decimalLongitude":-81.3137,"name":"Trichechus"},{"decimalLatitude":49.1684,"decimalLongitude":-123.1956,"name":"Canis"},{"decimalLatitude":30.501,"decimalLongitude":-98.8228,"name":"Otospermophilus"},{"decimalLatitude":36.6207,"decimalLongitude":-121.9059,"name":"Phoca"},{"decimalLatitude":44.9225,"decimalLongitude":-93.3599,"name":"Ondatra"},{"decimalLatitude":29.9998,"decimalLongitude":-90.1694,"name":"Sciurus"},{"decimalLatitude":38.2392,"decimalLongitude":-3.9402,"name":"Miniopterus"},{"decimalLatitude":42.6112,"decimalLongitude":-71.5745,"name":"Didelphis"},{"decimalLatitude":-1.2622,"decimalLongitude":36.8245,"name":"Cercopithecus"},{"decimalLatitude":41.265,"decimalLongitude":-81.4821,"name":"Didelphis"},{"decimalLatitude":-27.5637,"decimalLongitude":31.2614,"name":"Aepyceros"},{"decimalLatitude":3.4552,"decimalLongitude":-72.2214,"name":"Cerdocyon"},{"decimalLatitude":42.9725,"decimalLongitude":-81.2898,"name":"Sciurus"},{"decimalLatitude":28.7871,"decimalLongitude":-82.3387,"name":"Odocoileus"},{"decimalLatitude":70.4262,"decimalLongitude":28.5124,"name":"Alces"},{"decimalLatitude":59.5143,"decimalLongitude":9.3397,"name":"Cervus"},{"decimalLatitude":59.7774,"decimalLongitude":10.4088,"name":"Sciurus"},{"decimalLatitude":69.5226,"decimalLongitude":20.2139,"name":"Alces"},{"decimalLatitude":61.6076,"decimalLongitude":9.7089,"name":"Sorex"},{"decimalLatitude":60.7769,"decimalLongitude":11.3516,"name":"Sciurus"},{"decimalLatitude":61.1634,"decimalLongitude":5.9202,"name":"Myodes"},{"decimalLatitude":59.8979,"decimalLongitude":10.5924,"name":"Capreolus"},{"decimalLatitude":59.992,"decimalLongitude":10.9209,"name":"Sciurus"},{"decimalLatitude":59.6811,"decimalLongitude":10.6611,"name":"Sciurus"},{"decimalLatitude":63.1827,"decimalLongitude":8.7358,"name":"Sciurus"},{"decimalLatitude":61.5808,"decimalLongitude":9.8959,"name":"Sciurus"},{"decimalLatitude":62.4382,"decimalLongitude":6.4064,"name":"Cervus"},{"decimalLatitude":59.9707,"decimalLongitude":10.9288,"name":"Sciurus"},{"decimalLatitude":63.4044,"decimalLongitude":10.7951,"name":"Sciurus"},{"decimalLatitude":59.9444,"decimalLongitude":10.9251,"name":"Sciurus"},{"decimalLatitude":60.7971,"decimalLongitude":9.5412,"name":"Sciurus"},{"decimalLatitude":59.881,"decimalLongitude":11.2385,"name":"Sciurus"},{"decimalLatitude":59.4672,"decimalLongitude":11.6471,"name":"Sciurus"},{"decimalLatitude":60.0651,"decimalLongitude":6.5314,"name":"Sciurus"},{"decimalLatitude":64.5286,"decimalLongitude":11.3129,"name":"Felis"},{"decimalLatitude":59.9389,"decimalLongitude":10.6651,"name":"Capreolus"},{"decimalLatitude":69.334,"decimalLongitude":18.8929,"name":"Sciurus"},{"decimalLatitude":60.2245,"decimalLongitude":11.0205,"name":"Sciurus"},{"decimalLatitude":59.669,"decimalLongitude":9.6699,"name":"Sciurus"},{"decimalLatitude":60.9288,"decimalLongitude":11.006,"name":"Sciurus"},{"decimalLatitude":59.7511,"decimalLongitude":10.455,"name":"Sciurus"},{"decimalLatitude":63.3532,"decimalLongitude":10.2507,"name":"Sciurus"},{"decimalLatitude":60.8016,"decimalLongitude":10.8552,"name":"Sciurus"},{"decimalLatitude":69.9365,"decimalLongitude":23.2489,"name":"Capreolus"},{"decimalLatitude":59.6628,"decimalLongitude":10.6432,"name":"Sciurus"},{"decimalLatitude":61.4843,"decimalLongitude":9.3754,"name":"Sciurus"},{"decimalLatitude":66.0947,"decimalLongitude":13.8143,"name":"Sciurus"},{"decimalLatitude":59.6741,"decimalLongitude":10.8103,"name":"Sciurus"},{"decimalLatitude":58.1095,"decimalLongitude":6.9322,"name":"Sciurus"},{"decimalLatitude":66.1641,"decimalLongitude":13.9741,"name":"Vulpes"},{"decimalLatitude":60.8828,"decimalLongitude":11.2056,"name":"Capreolus"},{"decimalLatitude":66.1641,"decimalLongitude":13.9741,"name":"Alces"},{"decimalLatitude":60.4136,"decimalLongitude":11.4748,"name":"Sciurus"},{"decimalLatitude":60.0329,"decimalLongitude":10.013,"name":"Sciurus"},{"decimalLatitude":61.0856,"decimalLongitude":10.4722,"name":"Alces"},{"decimalLatitude":60.8461,"decimalLongitude":10.961,"name":"Sciurus"},{"decimalLatitude":59.4947,"decimalLongitude":6.2547,"name":"Felis"},{"decimalLatitude":59.4004,"decimalLongitude":10.6569,"name":"Sciurus"},{"decimalLatitude":64.2272,"decimalLongitude":12.3494,"name":"Sciurus"},{"decimalLatitude":61.1013,"decimalLongitude":10.7151,"name":"Sciurus"},{"decimalLatitude":61.7261,"decimalLongitude":9.5479,"name":"Sciurus"},{"decimalLatitude":60.8799,"decimalLongitude":10.9468,"name":"Alces"},{"decimalLatitude":60.6849,"decimalLongitude":11.3885,"name":"Sciurus"},{"decimalLatitude":60.9104,"decimalLongitude":11.615,"name":"Capreolus"},{"decimalLatitude":65.2815,"decimalLongitude":12.1637,"name":"Felis"},{"decimalLatitude":58.107,"decimalLongitude":7.9496,"name":"Capreolus"},{"decimalLatitude":59.4226,"decimalLongitude":10.6834,"name":"Felis"},{"decimalLatitude":64.0428,"decimalLongitude":13.8948,"name":"Gulo"},{"decimalLatitude":63.2557,"decimalLongitude":10.4382,"name":"Sciurus"},{"decimalLatitude":60.6608,"decimalLongitude":10.4713,"name":"Sciurus"},{"decimalLatitude":35.1159,"decimalLongitude":-119.3875,"name":"Ammospermophilus"},{"decimalLatitude":59.9457,"decimalLongitude":11.0311,"name":"Capreolus"},{"decimalLatitude":63.2495,"decimalLongitude":10.4387,"name":"Vulpes"},{"decimalLatitude":63.634,"decimalLongitude":8.8604,"name":"Cervus"},{"decimalLatitude":63.778,"decimalLongitude":11.4942,"name":"Sciurus"},{"decimalLatitude":59.9838,"decimalLongitude":11.1449,"name":"Sciurus"},{"decimalLatitude":60.6534,"decimalLongitude":4.7882,"name":"Phoca"},{"decimalLatitude":59.1301,"decimalLongitude":11.7009,"name":"Neovison"},{"decimalLatitude":50.793,"decimalLongitude":4.988,"name":"Rattus"},{"decimalLatitude":51.0643,"decimalLongitude":3.6781,"name":"Oryctolagus"},{"decimalLatitude":51.1672,"decimalLongitude":3.5728,"name":"Oryctolagus"},{"decimalLatitude":51.1212,"decimalLongitude":3.3843,"name":"Oryctolagus"},{"decimalLatitude":50.7783,"decimalLongitude":5.4329,"name":"Oryctolagus"},{"decimalLatitude":50.8803,"decimalLongitude":4.31,"name":"Oryctolagus"},{"decimalLatitude":-41.6606,"decimalLongitude":145.9527,"name":"Macropus"},{"decimalLatitude":-1.0014,"decimalLongitude":29.6973,"name":"Allochrocebus"},{"decimalLatitude":64.2211,"decimalLongitude":12.3138,"name":"Alces"},{"decimalLatitude":63.778,"decimalLongitude":11.4942,"name":"Capreolus"},{"decimalLatitude":20.7497,"decimalLongitude":-103.5606,"name":"Didelphis"},{"decimalLatitude":38.9764,"decimalLongitude":-76.9455,"name":"Sciurus"},{"decimalLatitude":27.6009,"decimalLongitude":-97.5035,"name":"Sus"},{"decimalLatitude":-41.2955,"decimalLongitude":174.6897,"name":"Oryctolagus"},{"decimalLatitude":-62.385,"decimalLongitude":-58.8359,"name":"Balaenoptera"},{"decimalLatitude":29.31,"decimalLongitude":-82.43,"name":"Gomphotheriidae"},{"decimalLatitude":39.829,"decimalLongitude":-74.9905,"name":"Procyon"},{"decimalLatitude":-1.3602,"decimalLongitude":36.72,"name":"Atelerix"},{"decimalLatitude":59.5958,"decimalLongitude":13.5979,"name":"Sus"},{"decimalLatitude":59.5651,"decimalLongitude":16.8666,"name":"Neovison"},{"decimalLatitude":62.2544,"decimalLongitude":16.249,"name":"Lutra"},{"decimalLatitude":63.7963,"decimalLongitude":20.4519,"name":"Lepus"},{"decimalLatitude":59.2166,"decimalLongitude":18.0629,"name":"Castor"},{"decimalLatitude":57.7289,"decimalLongitude":12.1405,"name":"Sus"},{"decimalLatitude":48.8293,"decimalLongitude":12.1734,"name":"Capreolus"},{"decimalLatitude":49.9795,"decimalLongitude":8.5092,"name":"Dama"},{"decimalLatitude":52.4894,"decimalLongitude":10.5619,"name":"Castor"},{"decimalLatitude":51.4102,"decimalLongitude":9.8508,"name":"Capreolus"},{"decimalLatitude":53.2259,"decimalLongitude":10.3581,"name":"Capreolus"},{"decimalLatitude":50.4822,"decimalLongitude":6.6233,"name":"Castor"},{"decimalLatitude":49.1167,"decimalLongitude":10.3977,"name":"Lepus"},{"decimalLatitude":51.3918,"decimalLongitude":12.369,"name":"Lepus"},{"decimalLatitude":48.5526,"decimalLongitude":8.9321,"name":"Vulpes"},{"decimalLatitude":53.9527,"decimalLongitude":11.2339,"name":"Vulpes"},{"decimalLatitude":52.5401,"decimalLongitude":10.8692,"name":"Vulpes"},{"decimalLatitude":52.5289,"decimalLongitude":10.3511,"name":"Castor"},{"decimalLatitude":52.0028,"decimalLongitude":9.8602,"name":"Capreolus"},{"decimalLatitude":53.8999,"decimalLongitude":10.7465,"name":"Sciurus"},{"decimalLatitude":50.1371,"decimalLongitude":8.6885,"name":"Sciurus"},{"decimalLatitude":51.2927,"decimalLongitude":12.6418,"name":"Sciurus"},{"decimalLatitude":50.64,"decimalLongitude":7.1773,"name":"Sciurus"},{"decimalLatitude":52.5379,"decimalLongitude":10.1514,"name":"Sciurus"},{"decimalLatitude":51.1994,"decimalLongitude":6.7553,"name":"Sciurus"},{"decimalLatitude":51.8758,"decimalLongitude":7.2611,"name":"Myocastor"},{"decimalLatitude":52.1023,"decimalLongitude":9.7741,"name":"Capreolus"},{"decimalLatitude":53.5043,"decimalLongitude":14.1169,"name":"Castor"},{"decimalLatitude":48.874,"decimalLongitude":10.4571,"name":"Dama"},{"decimalLatitude":-37.8854,"decimalLongitude":145.3219,"name":"Tachyglossus"},{"decimalLatitude":45.3206,"decimalLongitude":7.8992,"name":"Myocastor"},{"decimalLatitude":6.8058,"decimalLongitude":-74.2134,"name":"Sciurus"},{"decimalLatitude":6.8039,"decimalLongitude":-74.2129,"name":"Leopardus"},{"decimalLatitude":-31.4559,"decimalLongitude":152.8214,"name":"Trichosurus"},{"decimalLatitude":-32.389,"decimalLongitude":150.8887,"name":"Macropus"},{"decimalLatitude":-33.211,"decimalLongitude":151.485,"name":"Petaurus"},{"decimalLatitude":-32.4237,"decimalLongitude":150.8729,"name":"Trichosurus"},{"decimalLatitude":-32.9477,"decimalLongitude":151.5909,"name":"Nyctophilus"},{"decimalLatitude":-29.181,"decimalLongitude":152.4565,"name":"Vespadelus"},{"decimalLatitude":-28.971,"decimalLongitude":153.4388,"name":"Wallabia"},{"decimalLatitude":-30.5603,"decimalLongitude":152.2013,"name":"Antechinus"},{"decimalLatitude":-35.7307,"decimalLongitude":148.4976,"name":"Vulpes"},{"decimalLatitude":-37.3558,"decimalLongitude":149.7167,"name":"Petaurus"},{"decimalLatitude":-35.6026,"decimalLongitude":149.517,"name":"Petauroides"},{"decimalLatitude":-34.8314,"decimalLongitude":150.539,"name":"Vespadelus"},{"decimalLatitude":-32.3872,"decimalLongitude":150.8885,"name":"Vulpes"},{"decimalLatitude":53.7608,"decimalLongitude":-1.4481,"name":"Talpa"},{"decimalLatitude":53.0155,"decimalLongitude":-2.2255,"name":"Vulpes"},{"decimalLatitude":54.297,"decimalLongitude":-0.6475,"name":"Sciurus"},{"decimalLatitude":52.2294,"decimalLongitude":-3.422,"name":"Mustela"},{"decimalLatitude":52.0216,"decimalLongitude":0.4538,"name":"Vulpes"},{"decimalLatitude":52.0305,"decimalLongitude":0.4753,"name":"Muntiacus"},{"decimalLatitude":57.2898,"decimalLongitude":-4.3746,"name":"Oryctolagus"},{"decimalLatitude":53.2554,"decimalLongitude":-3.0331,"name":"Sciurus"},{"decimalLatitude":53.1156,"decimalLongitude":-1.316,"name":"Capreolus"},{"decimalLatitude":52.0088,"decimalLongitude":0.4648,"name":"Dama"},{"decimalLatitude":55.934,"decimalLongitude":-2.9851,"name":"Talpa"},{"decimalLatitude":53.369,"decimalLongitude":-1.8155,"name":"Oryctolagus"},{"decimalLatitude":51.364,"decimalLongitude":1.2588,"name":"Sciurus"},{"decimalLatitude":49.49,"decimalLongitude":6.1,"name":"Erinaceus"},{"decimalLatitude":-33.4162,"decimalLongitude":150.2604,"name":"Vulpes"},{"decimalLatitude":-33.3887,"decimalLongitude":150.2646,"name":"Equus"},{"decimalLatitude":-33.4142,"decimalLongitude":150.2238,"name":"Vombatus"},{"decimalLatitude":-36.5827,"decimalLongitude":149.3855,"name":"Antechinus"},{"decimalLatitude":-33.6931,"decimalLongitude":150.8752,"name":"Vulpes"},{"decimalLatitude":-33.6931,"decimalLongitude":150.8752,"name":"Chalinolobus"},{"decimalLatitude":43.2679,"decimalLongitude":-79.9182,"name":"Odocoileus"},{"decimalLatitude":56.0283,"decimalLongitude":14.1465,"name":"Lutra"},{"decimalLatitude":66.6091,"decimalLongitude":19.8096,"name":"Capreolus"},{"decimalLatitude":63.7628,"decimalLongitude":19.8668,"name":"Mustela"},{"decimalLatitude":59.0258,"decimalLongitude":17.6396,"name":"Dama"},{"decimalLatitude":56.5939,"decimalLongitude":12.9336,"name":"Capreolus"},{"decimalLatitude":56.2506,"decimalLongitude":16.4223,"name":"Dama"},{"decimalLatitude":60.1458,"decimalLongitude":16.3213,"name":"Sciurus"},{"decimalLatitude":56.7043,"decimalLongitude":12.9068,"name":"Dama"},{"decimalLatitude":55.6745,"decimalLongitude":13.5119,"name":"Sus"},{"decimalLatitude":56.7108,"decimalLongitude":12.901,"name":"Capreolus"},{"decimalLatitude":56.1362,"decimalLongitude":12.6632,"name":"Capreolus"},{"decimalLatitude":56.1692,"decimalLongitude":12.7623,"name":"Capreolus"},{"decimalLatitude":59.5414,"decimalLongitude":16.668,"name":"Vulpes"},{"decimalLatitude":58.3252,"decimalLongitude":15.4674,"name":"Dama"},{"decimalLatitude":57.1168,"decimalLongitude":13.6859,"name":"Capreolus"},{"decimalLatitude":59.8963,"decimalLongitude":16.7968,"name":"Vulpes"},{"decimalLatitude":55.6879,"decimalLongitude":13.1825,"name":"Sciurus"},{"decimalLatitude":55.9215,"decimalLongitude":14.3289,"name":"Capreolus"},{"decimalLatitude":56.915,"decimalLongitude":14.5021,"name":"Vulpes"},{"decimalLatitude":58.3161,"decimalLongitude":15.6679,"name":"Capreolus"},{"decimalLatitude":58.4894,"decimalLongitude":11.4489,"name":"Mustela"},{"decimalLatitude":56.6118,"decimalLongitude":14.1917,"name":"Vulpes"},{"decimalLatitude":57.8911,"decimalLongitude":11.6627,"name":"Phoca"},{"decimalLatitude":56.419,"decimalLongitude":16.3928,"name":"Lepus"},{"decimalLatitude":57.9718,"decimalLongitude":12.6612,"name":"Capreolus"},{"decimalLatitude":59.8434,"decimalLongitude":18.7314,"name":"Lutra"},{"decimalLatitude":59.0021,"decimalLongitude":17.1728,"name":"Dama"},{"decimalLatitude":59.0378,"decimalLongitude":17.3324,"name":"Lutra"},{"decimalLatitude":55.7851,"decimalLongitude":13.7815,"name":"Sus"},{"decimalLatitude":57.7323,"decimalLongitude":11.9692,"name":"Sciurus"},{"decimalLatitude":59.2928,"decimalLongitude":18.1002,"name":"Sciurus"},{"decimalLatitude":59.6747,"decimalLongitude":6.4146,"name":"Vulpes"},{"decimalLatitude":60.3648,"decimalLongitude":5.3421,"name":"Rattus"},{"decimalLatitude":59.3065,"decimalLongitude":4.8584,"name":"Halichoerus"},{"decimalLatitude":58.1284,"decimalLongitude":8.1515,"name":"Phoca"},{"decimalLatitude":59.6714,"decimalLongitude":6.4085,"name":"Lepus"},{"decimalLatitude":59.8062,"decimalLongitude":10.6842,"name":"Sciurus"},{"decimalLatitude":59.6511,"decimalLongitude":10.5351,"name":"Martes"},{"decimalLatitude":59.9918,"decimalLongitude":10.7794,"name":"Alces"},{"decimalLatitude":59.7863,"decimalLongitude":5.1264,"name":"Rattus"},{"decimalLatitude":68.1483,"decimalLongitude":15.4535,"name":"Alces"},{"decimalLatitude":68.0395,"decimalLongitude":15.382,"name":"Alces"},{"decimalLatitude":58.9398,"decimalLongitude":6.0908,"name":"Capreolus"},{"decimalLatitude":62.9854,"decimalLongitude":27.6959,"name":"Sciurus"},{"decimalLatitude":60.5418,"decimalLongitude":25.9949,"name":"Felis"},{"decimalLatitude":60.6943,"decimalLongitude":21.7473,"name":"Apodemus"},{"decimalLatitude":60.6126,"decimalLongitude":24.5316,"name":"Capreolus"},{"decimalLatitude":60.8133,"decimalLongitude":26.3539,"name":"Mustela"},{"decimalLatitude":61.5244,"decimalLongitude":21.8252,"name":"Sciurus"},{"decimalLatitude":45.1048,"decimalLongitude":-73.2155,"name":"Odocoileus"},{"decimalLatitude":51.9,"decimalLongitude":4.9,"name":"Capreolus"},{"decimalLatitude":52.3,"decimalLongitude":5.8,"name":"Sus"},{"decimalLatitude":51.4,"decimalLongitude":3.55,"name":"Phoca"},{"decimalLatitude":52.15,"decimalLongitude":5.05,"name":"Capreolus"},{"decimalLatitude":51.7,"decimalLongitude":5.7,"name":"Capreolus"},{"decimalLatitude":51.7,"decimalLongitude":5.6,"name":"Capreolus"},{"decimalLatitude":51.6,"decimalLongitude":5.1,"name":"Capreolus"},{"decimalLatitude":51.8,"decimalLongitude":5.95,"name":"Meles"},{"decimalLatitude":52.15,"decimalLongitude":4.45,"name":"Rattus"},{"decimalLatitude":52,"decimalLongitude":6.25,"name":"Lepus"},{"decimalLatitude":51.7,"decimalLongitude":3.65,"name":"Phoca"},{"decimalLatitude":52.45,"decimalLongitude":6.05,"name":"Lepus"},{"decimalLatitude":51.7,"decimalLongitude":5.65,"name":"Mustela"},{"decimalLatitude":51.95,"decimalLongitude":6.25,"name":"Lepus"},{"decimalLatitude":52.05,"decimalLongitude":4.3,"name":"Sciurus"},{"decimalLatitude":52.05,"decimalLongitude":4.3,"name":"Sciurus"},{"decimalLatitude":52.05,"decimalLongitude":4.9,"name":"Lepus"},{"decimalLatitude":51.7,"decimalLongitude":5.75,"name":"Lepus"},{"decimalLatitude":52.7,"decimalLongitude":4.6,"name":"Phocoena"},{"decimalLatitude":51.85,"decimalLongitude":4.5,"name":"Apodemus"},{"decimalLatitude":51.85,"decimalLongitude":4.2,"name":"Capreolus"},{"decimalLatitude":53.15,"decimalLongitude":5.75,"name":"Capreolus"},{"decimalLatitude":52.85,"decimalLongitude":6,"name":"Capreolus"},{"decimalLatitude":51.7,"decimalLongitude":3.8,"name":"Phoca"},{"decimalLatitude":53.15,"decimalLongitude":7,"name":"Capreolus"},{"decimalLatitude":52.05,"decimalLongitude":4.7,"name":"Mustela"},{"decimalLatitude":51.75,"decimalLongitude":4.2,"name":"Capreolus"},{"decimalLatitude":52.9,"decimalLongitude":6.8,"name":"Capreolus"},{"decimalLatitude":52.45,"decimalLongitude":4.5,"name":"Halichoerus"},{"decimalLatitude":53,"decimalLongitude":6.8,"name":"Capreolus"},{"decimalLatitude":52.45,"decimalLongitude":4.6,"name":"Lepus"},{"decimalLatitude":51.5,"decimalLongitude":5.55,"name":"Lepus"},{"decimalLatitude":51.7,"decimalLongitude":5.55,"name":"Plecotus"},{"decimalLatitude":52.15,"decimalLongitude":5.2,"name":"Capreolus"}]}
